CHANGELOG.txt
LICENCE.txt
MANIFEST.in
README.txt
setup.py
pyhirtlib/__init__.py
pyhirtlib/events.py
pyhirtlib/hi_context.py
pyhirtlib/requirements.txt
pyhirtlib.egg-info/PKG-INFO
pyhirtlib.egg-info/SOURCES.txt
pyhirtlib.egg-info/dependency_links.txt
pyhirtlib.egg-info/top_level.txt
pyhirtlib/commons/__init__.py
pyhirtlib/commons/binary_reader_extension.py
pyhirtlib/commons/enums_struct_def.py
pyhirtlib/commons/logs.py
pyhirtlib/commons/to_debug.py
pyhirtlib/commons/exception/__init__.py
pyhirtlib/commons/exception/read_tag_struct_exception.py
pyhirtlib/configs/__init__.py
pyhirtlib/configs/config.cfg
pyhirtlib/configs/config.py
pyhirtlib/tag_reader/__init__.py
pyhirtlib/tag_reader/tag_file.py
pyhirtlib/tag_reader/tag_layouts.py
pyhirtlib/tag_reader/tag_parse.py
pyhirtlib/tag_reader/var_name.py
pyhirtlib/tag_reader/headers/__init__.py
pyhirtlib/tag_reader/headers/data_block_table.py
pyhirtlib/tag_reader/headers/data_reference_table.py
pyhirtlib/tag_reader/headers/general_class.py
pyhirtlib/tag_reader/headers/string_id_table.py
pyhirtlib/tag_reader/headers/table_entry.py
pyhirtlib/tag_reader/headers/tag_file_header.py
pyhirtlib/tag_reader/headers/tag_ref_table.py
pyhirtlib/tag_reader/headers/tag_reference_fix_uptable.py
pyhirtlib/tag_reader/headers/tag_struct_table.py
pyhirtlib/tag_reader/headers/zone_set.py
pyhirtlib/tag_reader/tag_elemnts/__init__.py
pyhirtlib/tag_reader/tag_elemnts/default_struct_factory.py
pyhirtlib/tag_reader/tag_elemnts/defult_atomic_factory.py
pyhirtlib/tag_reader/tag_elemnts/tag_element.py
pyhirtlib/tag_reader/tag_elemnts/tag_element_atomic.py
pyhirtlib/tag_reader/tag_elemnts/tag_element_dict.py
pyhirtlib/tag_reader/tag_elemnts/tag_element_factory.py
pyhirtlib/tag_reader/tag_elemnts/tag_element_list.py
pyhirtlib/tag_reader/tag_elemnts/tag_element_reader.py
pyhirtlib/tag_reader/tag_elemnts/tag_element_type.py
pyhirtlib/tag_reader/tag_elemnts/default_atm_readers/__init__.py
pyhirtlib/tag_reader/tag_elemnts/default_atm_readers/core_readers.py
pyhirtlib/tag_reader/tag_elemnts/default_atm_readers/enum_flags_block.py
