Metadata-Version: 2.1
Name: pyhirtlib
Version: 0.0.18
Summary: A tag reader for halo infinite
Home-page: 
Author: Jorge Glez
Author-email: urium86@gmail.com
License: MIT
Keywords: halo infinite,tags,module
Classifier: Development Status :: 5 - Production/Stable
Classifier: Intended Audience :: Education
Classifier: Operating System :: Microsoft :: Windows :: Windows 10
Classifier: License :: OSI Approved :: MIT License
Classifier: Programming Language :: Python :: 3
License-File: LICENCE.txt
